addon_tvg/__init__.py
addon_tvg/evalexpress.py
addon_tvg/grapp.py
addon_tvg/sumall.py
addon_tvg_karjakak-0.2.3.dist-info/METADATA
addon_tvg_karjakak-0.2.3.dist-info/WHEEL
addon_tvg_karjakak-0.2.3.dist-info/top_level.txt
addon_tvg_karjakak-0.2.3.dist-info/RECORD
