Metadata-Version: 2.1
Name: addon-tvg-karjakak
Version: 0.2.3
Summary: Add on functions for TVG.
Home-page: https://github.com/kakkarja/FreeTVG
Author: karjakak
Author-email: kakkarja.github@gmail.com
License: BSD3 License
Classifier: Environment :: Win32 (MS Windows)
Classifier: Environment :: MacOS X
Classifier: Intended Audience :: End Users/Desktop
Classifier: Topic :: Text Editors :: Text Processing
Classifier: Programming Language :: Python :: 3.10
Classifier: License :: OSI Approved :: BSD License
Requires-Python: >=3.10
Requires-Dist: matplotlib (>=3.5.3)
Requires-Dist: treeview-karjakak (>=1.8.4)
